LICENSE.txt
MANIFEST.in
README.md
TODO.md
requirements.txt
setup.py
gifshare/__init__.py
gifshare/__main__.py
gifshare.egg-info/PKG-INFO
gifshare.egg-info/SOURCES.txt
gifshare.egg-info/dependency_links.txt
gifshare.egg-info/entry_points.txt
gifshare.egg-info/not-zip-safe
gifshare.egg-info/requires.txt
gifshare.egg-info/top_level.txt
requirements/_base.txt
requirements/development.txt