Metadata-Version: 1.1
Name: gifshare
Version: 0.0.4
Summary: Store images in S3
Home-page: https://github.com/judy2k/gifshare
Author: Mark Smith
Author-email: mark.smith@practicalpoetry.co.uk
License: MIT License
Platform: UNKNOWN
Classifier: Development Status :: 4 - Beta
Classifier: Environment :: Console
Classifier: License :: OSI Approved :: MIT License
Classifier: Operating System :: OS Independent
Classifier: Programming Language :: Python
Classifier: Programming Language :: Python :: 2.7
Classifier: Programming Language :: Python :: 3
Classifier: Programming Language :: Python :: 3.3
Classifier: Programming Language :: Python :: 3.4
